django_qiyu_sso/__init__.py
django_qiyu_sso/admin.py
django_qiyu_sso/apps.py
django_qiyu_sso/checks.py
django_qiyu_sso/logic/__init__.py
django_qiyu_sso/logic/user.py
django_qiyu_sso/migrations/__init__.py
django_qiyu_sso/models.py
django_qiyu_sso/settings.py
django_qiyu_sso/templates/user/oauth_login_failure.html
django_qiyu_sso/tests.py
django_qiyu_sso/urls.py
django_qiyu_sso/views/__init__.py
django_qiyu_sso/views/admin_login.py
django_qiyu_sso/views/login.py
django_qiyu_sso/views/login_success.py
django_qiyu_sso/views/logout.py
django_qiyu_sso-0.6.6.dist-info/WHEEL
django_qiyu_sso-0.6.6.dist-info/METADATA
django_qiyu_sso-0.6.6.dist-info/RECORD
