Metadata-Version: 2.1
Name: django-qiyu-sso
Version: 0.6.6
Summary: QiYu SSO intergation for Django
Home-page: https://www.qiyutech.tech/
Author: dev
Author-email: dev@qiyutech.tech
Requires-Python: >=3.9,<3.11
Classifier: Programming Language :: Python :: 3
Classifier: Programming Language :: Python :: 3.9
Classifier: Programming Language :: Python :: 3.10
Requires-Dist: django (>=4.0,<4.2)
Requires-Dist: django-qiyu-utils (>=0.4.4,<0.5)
Requires-Dist: qiyu-sso (>=0.2.14,<0.3)
